fdint/__init__.py
fdint/_fdint.cp36-win_amd64.pyd
fdint/dfd.cp36-win_amd64.pyd
fdint/dgfd.cp36-win_amd64.pyd
fdint/fd.cp36-win_amd64.pyd
fdint/gfd.cp36-win_amd64.pyd
fdint/ifd.cp36-win_amd64.pyd
fdint/scfd.cp36-win_amd64.pyd
fdint/version.py
fdint/examples/__init__.py
fdint/examples/plot.py
fdint/tests/__init__.py
fdint/tests/__main__.py
fdint/tests/test_fd.py
fdint/tests/test_gfd.py
fdint/tests/test_ifd.py
fdint/tests/test_scfd.py
fdint-2.0.2.data/data/__init__.pxd
fdint-2.0.2.data/data/_fdint.pxd
fdint-2.0.2.data/data/scfd.pxd
fdint-2.0.2.dist-info/LICENSE.txt
fdint-2.0.2.dist-info/METADATA
fdint-2.0.2.dist-info/WHEEL
fdint-2.0.2.dist-info/top_level.txt
fdint-2.0.2.dist-info/RECORD
