Metadata-Version: 1.0
Name: fdint
Version: 2.0.2
Summary: A free, open-source python package for quickly and precisely approximating Fermi-Dirac integrals.
Home-page: http://scott-maddox.github.io/fdint
Author: Scott J. Maddox
Author-email: smaddox@utexas.edu
License: BSD
Platform: UNKNOWN
